<annotation>
	<folder>dog</folder>
	<filename>dog_103.jpg</filename>
	<path>/media/akash/Local Disk/datasets/dog/585dd87e-60f4-497b-8a2b-f0fc2965091d_560_420.jpg</path>
	<source>
		<database>Unknown</database>
	</source>
	<size>
		<width>560</width>
		<height>420</height>
		<depth>3</depth>
	</size>
	<segmented>0</segmented>
	<object>
		<name>dog</name>
		<pose>Unspecified</pose>
		<truncated>0</truncated>
		<difficult>0</difficult>
		<bndbox>
			<xmin>128</xmin>
			<ymin>67</ymin>
			<xmax>275</xmax>
			<ymax>372</ymax>
		</bndbox>
	</object>
	<object>
		<name>dog</name>
		<pose>Unspecified</pose>
		<truncated>0</truncated>
		<difficult>0</difficult>
		<bndbox>
			<xmin>273</xmin>
			<ymin>52</ymin>
			<xmax>444</xmax>
			<ymax>391</ymax>
		</bndbox>
	</object>
</annotation>