<annotation>
	<folder>Polar+Bear</folder>
	<filename>Polar+Bear_79.jpg</filename>
	<path>/home/anik/ML Workspace/Endangered Species/images/Polar+Bear/polar-bear-2.jpg</path>
	<source>
		<database>Unknown</database>
	</source>
	<size>
		<width>858</width>
		<height>536</height>
		<depth>3</depth>
	</size>
	<segmented>0</segmented>
	<object>
		<name>Polar Bear</name>
		<pose>Unspecified</pose>
		<truncated>0</truncated>
		<difficult>0</difficult>
		<bndbox>
			<xmin>62</xmin>
			<ymin>31</ymin>
			<xmax>762</xmax>
			<ymax>514</ymax>
		</bndbox>
	</object>
</annotation>